mcp_server_lib/__init__.py
mcp_server_lib/browser.py
mcp_server_lib/py.typed
mcp_server_lib-0.1.4.dist-info/METADATA
mcp_server_lib-0.1.4.dist-info/WHEEL
mcp_server_lib-0.1.4.dist-info/RECORD
