Metadata-Version: 2.4
Name: mcp-server-lib
Version: 0.1.4
Summary: MCP Server Library
Author-email: saltfishpr <saltfishpr@gmail.com>
Requires-Python: >=3.13
Requires-Dist: playwright>=1.51.0
